pkg_common/__init__.py
pkg_common/botitems.py
pkg_common/filestores.py
pkg_common/pipelines.py
pkg_common/services.py
pkg_common/utility.py
pkg_common-0.6.dist-info/LICENSE
pkg_common-0.6.dist-info/METADATA
pkg_common-0.6.dist-info/WHEEL
pkg_common-0.6.dist-info/top_level.txt
pkg_common-0.6.dist-info/RECORD
